nonebot_plugin_fuck/__init__.py
nonebot_plugin_fuck/text.txt
nonebot_plugin_fuck-1.2.1.dist-info/LICENSE
nonebot_plugin_fuck-1.2.1.dist-info/METADATA
nonebot_plugin_fuck-1.2.1.dist-info/WHEEL
nonebot_plugin_fuck-1.2.1.dist-info/RECORD
