Metadata-Version: 2.3
Name: nonebot_plugin_fuck
Version: 1.2.1
Summary: NoneBot 机器人攻击群友插件
Home-page: https://github.com/YTSakura233/nonebot_plugin_fuck
License: MIT
Keywords: nonebot,nonebot2,bilibili
Author: YTSakura
Requires-Python: >=3.8,<4.0
Classifier: License :: OSI Approved :: MIT License
Classifier: Programming Language :: Python :: 3
Classifier: Programming Language :: Python :: 3.8
Classifier: Programming Language :: Python :: 3.9
Classifier: Programming Language :: Python :: 3.10
Classifier: Programming Language :: Python :: 3.11
Classifier: Programming Language :: Python :: 3.12
Classifier: Programming Language :: Python :: 3.13
Requires-Dist: nonebot-plugin-send-anything-anywhere (>=0,<1)
Requires-Dist: nonebot2 (>=2.1.1,<3.0.0)
Project-URL: Repository, https://github.com/YTSakura233/nonebot_plugin_fuck
